xor_cipher/__init__.py
xor_cipher/bytes.py
xor_cipher/core.py
xor_cipher/py.typed
xor_cipher/python.py
xor_cipher-5.0.2.dist-info/METADATA
xor_cipher-5.0.2.dist-info/WHEEL
xor_cipher-5.0.2.dist-info/licenses/LICENSE
xor_cipher-5.0.2.dist-info/RECORD
