Metadata-Version: 2.4
Name: xor-cipher
Version: 5.0.2
Summary: Simple, reusable and optimized XOR ciphers in Python.
Project-URL: Homepage, https://github.com/GDPSApp/xor-cipher-python
Project-URL: Documentation, https://xor-cipher.gdps.app/
Project-URL: Issues, https://github.com/GDPSApp/xor-cipher-python/issues
Project-URL: Repository, https://github.com/GDPSApp/xor-cipher-python
Author-email: GDPS App <hello@gdps.app>
License: MIT License
License-File: LICENSE
Keywords: cipher,python,xor
Classifier: Development Status :: 5 - Production/Stable
Classifier: Intended Audience :: Developers
Classifier: License :: OSI Approved :: MIT License
Classifier: Operating System :: OS Independent
Classifier: Programming Language :: Python
Classifier: Programming Language :: Python :: 3
Classifier: Programming Language :: Python :: 3.9
Classifier: Programming Language :: Python :: 3.10
Classifier: Programming Language :: Python :: 3.11
Classifier: Programming Language :: Python :: 3.12
Classifier: Programming Language :: Python :: 3.13
Classifier: Topic :: Utilities
Classifier: Typing :: Typed
Requires-Python: >=3.9
Requires-Dist: xor-cipher-core>=1.2.0
